xqr/__init__.py
xqr/cli.py
xqr/commands/__init__.py
xqr/commands/base.py
xqr/commands/create.py
xqr/commands/examples.py
xqr/commands/load.py
xqr/commands/ls.py
xqr/commands/query.py
xqr/commands/save.py
xqr/commands/server.py
xqr/commands/set.py
xqr/commands/shell.py
xqr/core/__init__.py
xqr/core/editor.py
xqr/core/examples.py
xqr/core/operations.py
xqr/core/parsers.py
xqr/core/xpath_utils.py
xqr/core.py
xqr/examples.py
xqr/jquery_syntax.py
xqr/server/__init__.py
xqr/server/handlers.py
xqr/server/server.py
xqr/server/static.py
xqr/server.py
xqr/state.py
xqr-0.1.3.dist-info/LICENSE
xqr-0.1.3.dist-info/METADATA
xqr-0.1.3.dist-info/WHEEL
xqr-0.1.3.dist-info/entry_points.txt
xqr-0.1.3.dist-info/RECORD
