Metadata-Version: 2.3
Name: xqr
Version: 0.1.3
Summary: Universal CLI tool for editing SVG, HTML, and XML files using XPath and CSS selectors
License: Apache-2.0
Keywords: xml,html,svg,xpath,css-selectors,cli,editor
Author: Tom Sapletta
Author-email: info@softreck.dev
Maintainer: Tom Sapletta
Maintainer-email: info@softreck.dev
Requires-Python: >=3.8.1,<4.0
Classifier: Development Status :: 4 - Beta
Classifier: Environment :: Console
Classifier: Environment :: Web Environment
Classifier: Intended Audience :: Developers
Classifier: Intended Audience :: System Administrators
Classifier: License :: OSI Approved :: Apache Software License
Classifier: Operating System :: OS Independent
Classifier: Programming Language :: Python :: 3
Classifier: Programming Language :: Python :: 3.8
Classifier: Programming Language :: Python :: 3.9
Classifier: Programming Language :: Python :: 3.10
Classifier: Programming Language :: Python :: 3.11
Classifier: Programming Language :: Python :: 3.12
Classifier: Topic :: Software Development :: Libraries :: Python Modules
Classifier: Topic :: Text Processing :: Markup :: HTML
Classifier: Topic :: Text Processing :: Markup :: XML
Provides-Extra: dev
Requires-Dist: beautifulsoup4 (>=4.12.0,<5.0.0)
Requires-Dist: black (>=23.0.0,<24.0.0) ; extra == "dev"
Requires-Dist: cssselect (>=1.2.0,<2.0.0)
Requires-Dist: flake8 (>=6.0.0,<7.0.0) ; extra == "dev"
Requires-Dist: lxml (>=4.9.0,<5.0.0)
Requires-Dist: mypy (>=1.5.0,<2.0.0) ; extra == "dev"
Requires-Dist: pre-commit (>=3.4.0,<4.0.0) ; extra == "dev"
Requires-Dist: pytest (>=7.4.0,<8.0.0) ; extra == "dev"
Requires-Dist: pytest-cov (>=4.1.0,<5.0.0) ; extra == "dev"
Project-URL: Bug Tracker, https://github.com/veridock/xqr/issues
Project-URL: Changelog, https://github.com/veridock/xqr/blob/main/CHANGELOG.md
Project-URL: Documentation, https://veridock.github.io/xqr
Project-URL: Homepage, https://github.com/veridock/xqr
Project-URL: Repository, https://github.com/veridock/xqr
